README.md
setup.py
logtime/__init__.py
logtime/logtime.py
logtime.egg-info/PKG-INFO
logtime.egg-info/SOURCES.txt
logtime.egg-info/dependency_links.txt
logtime.egg-info/entry_points.txt
logtime.egg-info/top_level.txt