Metadata-Version: 1.1
Name: logtime
Version: 1.0.0
Summary: UNKNOWN
Home-page: https://github.com/mtingers/logtime
Author: Matth Ingersoll
Author-email: matth@mtingers.com
License: BSD 2-Clause License
Platform: UNKNOWN
Classifier: Intended Audience :: System Administrators
Classifier: License :: OSI Approved :: BSD License
Classifier: Programming Language :: Python :: 2.7
Classifier: Programming Language :: Python :: 3
Classifier: Programming Language :: Python :: 3.4
Classifier: Programming Language :: Python :: 3.5
Classifier: Programming Language :: Python :: 3.6
Classifier: Programming Language :: Python :: 3.7
Classifier: Programming Language :: Python :: 3.8
Classifier: Programming Language :: Python :: 3.9
